kea_leases_to_json/__init__.py
kea_leases_to_json/cli.py
kea_leases_to_json/core.py
kea_leases_to_json-0.1.2.dist-info/licenses/LICENSE
kea_leases_to_json-0.1.2.dist-info/METADATA
kea_leases_to_json-0.1.2.dist-info/WHEEL
kea_leases_to_json-0.1.2.dist-info/entry_points.txt
kea_leases_to_json-0.1.2.dist-info/top_level.txt
kea_leases_to_json-0.1.2.dist-info/RECORD
