Metadata-Version: 2.4
Name: kea-leases-to-json
Version: 0.1.2
Summary: Convert Kea DHCP leases to JSON format
Author-email: Junior <cjuniorfox@gmail.com>
License: GNU General Public License v3.0 (GPLv3)
Project-URL: Homepage, http://github.com/cjuniorfox/kea-leases-to-json
Keywords: kea,dhcp,leases,json
Requires-Python: >=3.7
License-File: LICENSE
Requires-Dist: watchdog
Requires-Dist: pytest
Provides-Extra: test
Requires-Dist: pytest; extra == "test"
Dynamic: license-file
